vibe_tide_mcp_server.py
vibe_tide_mcp_server-0.1.0.dist-info/METADATA
vibe_tide_mcp_server-0.1.0.dist-info/WHEEL
vibe_tide_mcp_server-0.1.0.dist-info/entry_points.txt
vibe_tide_mcp_server-0.1.0.dist-info/licenses/LICENSE
vibe_tide_mcp_server-0.1.0.dist-info/RECORD
