Metadata-Version: 2.4
Name: vibe-tide-mcp-server
Version: 0.1.0
Summary: VibeTide MCP Server - A Model Context Protocol server for VibeTide platformer levels
Project-URL: Homepage, https://github.com/banjtheman/vibe_tide_mcp
Project-URL: Documentation, https://github.com/banjtheman/vibe_tide_mcp#readme
Project-URL: Repository, https://github.com/banjtheman/vibe_tide_mcp
Project-URL: Issues, https://github.com/banjtheman/vibe_tide_mcp/issues
Author-email: Banjo Obayomi <banjtheman@gmail.com>
License: MIT
License-File: LICENSE
Keywords: game,level-editor,mcp,platformer,server,vibe-tide
Classifier: Development Status :: 4 - Beta
Classifier: Intended Audience :: Developers
Classifier: License :: OSI Approved :: MIT License
Classifier: Programming Language :: Python :: 3
Classifier: Programming Language :: Python :: 3.10
Classifier: Programming Language :: Python :: 3.11
Classifier: Programming Language :: Python :: 3.12
Classifier: Topic :: Games/Entertainment
Classifier: Topic :: Software Development :: Libraries :: Python Modules
Requires-Python: >=3.10
Requires-Dist: fastmcp>=0.4.0
Requires-Dist: mcp>=1.0.0
Requires-Dist: pillow>=10.0.0
